LICENSE
MANIFEST.in
README.rst
setup.py
django_klingon.egg-info/PKG-INFO
django_klingon.egg-info/SOURCES.txt
django_klingon.egg-info/dependency_links.txt
django_klingon.egg-info/not-zip-safe
django_klingon.egg-info/top_level.txt
klingon/__init__.py
klingon/admin.py
klingon/compat.py
klingon/models.py
klingon/views.py
klingon/management/__init__.py
klingon/management/commands/__init__.py
klingon/management/commands/translatemodels.py
klingon/migrations/0001_initial.py
klingon/migrations/__init__.py
tests/__init__.py
tests/conftest.py
tests/test_api.py
tests/test_commands.py
tests/testapp/__init__.py
tests/testapp/models.py