Metadata-Version: 1.1
Name: django-klingon
Version: 0.0.8
Summary: django-klingon is an attempt to make django model translation suck but with no integrations pain in your app!
Home-page: http://github.com/angvp/django-klingon
Author: Rafael Capdevielle, Angel Velasquez
Author-email: angvp@archlinux.org
License: GPL
Platform: UNKNOWN
Classifier: Topic :: Internet :: WWW/HTTP :: Dynamic Content
Classifier: Intended Audience :: Developers
Classifier: Programming Language :: Python
Classifier: Programming Language :: Python :: 2.7
Classifier: Programming Language :: Python :: 3.4
Classifier: Programming Language :: Python :: 3.5
Classifier: Programming Language :: Python :: 3.6
Classifier: Programming Language :: Python :: 3.7
Classifier: Framework :: Django :: 1.11
Classifier: Framework :: Django :: 2.0
Classifier: Framework :: Django :: 2.1
Classifier: Development Status :: 5 - Production/Stable
Classifier: Operating System :: OS Independent
